[
    {
        "count": 28,
        "next": "https://gosgstg.malaysia.gov.my/public/cms/service/homepage_announcement/en/?offset=10&limit=20",
        "previous": null,
        "results": [
            {
                "Announcement": [
                    {
                        "id": "18",
                        "name": "LHDN provides e-filing of income tax refunds for Electronic Transfers",
                        "desc": "LHDN provides e-filing of income tax refunds for Electronic Transfers",
                        "text": "<p><span>MINIMUM REQUIREMENTS </span></p><p>&nbsp;</p><ul><li>Microsoft Windows 7 (latest service pack), Linux or Macintosh.</li><li>Internet Explorer 11.0, Microsoft Edge, 44.0 Mozilla Firefox, Google Chrome 46.0 or Safari 5.</li><li>TAXPAYER'S NEW FIRST TIME OR TO REPORT EARNINGS / above RM 450,000</li></ul><p>&nbsp;</p><p><span>Informed that taxpayers who first reported income equals or exceeds &pound; 450,000 through the delivery form for e-Filing must present / IRB branches close contact to make income verification. This procedure is to avoid the possibility of a mistake entering the amount of income by taxpayers. This procedure does not apply to taxpayers who made via e-Filing Tax Agent.</span></p><p><span lang=\"en\">This procedure does not apply to taxpayers who made via e-Filing Tax Agent.</span></p><p><span lang=\"en\">&nbsp;</span></p>",
                        "active": "True",
                        "insert_date": "2017-03-26 16:52:55.065626+00:00",
                        "last_modified": "2017-03-26 16:52:58.032053+00:00",
                        "idcategory": "Pengumuman",
                        "date_publish": "2017-03-26 16:00:00+00:00",
                        "date_end": "2017-03-29 16:00:00+00:00",
                        "link": "https://ez.hasil.gov.my/CI",
                        "year": "2017",
                        "archive": "False",
                        "title": ""
                    },
                    {
                        "id": "19",
                        "name": "MYEG - Create an account to access all our services including road tax renewal, PDRM summons checking, zakat payment, and more.",
                        "desc": "Create an account to access all our services including road tax renewal, PDRM summons checking",
                        "text": "<p>Please visit&nbsp;<a href=\"https://www.myeg.com.my/\" target=\"_blank\">https://www.myeg.com.my/</a> to&nbsp;&nbsp;Create an account to access all our services including road tax renewal, PDRM summons checking, zakat payment, and more.</p>",
                        "active": "True",
                        "insert_date": "2017-03-26 17:01:41.500298+00:00",
                        "last_modified": "2017-03-26 17:03:04.904738+00:00",
                        "idcategory": "Pengumuman",
                        "date_publish": "2017-03-26 16:00:00+00:00",
                        "date_end": "2017-03-29 16:00:00+00:00",
                        "link": "https://www.myeg.com.my",
                        "year": "2017",
                        "archive": "False",
                        "title": ""
                    },
                    {
                        "id": "17",
                        "name": "GAMMA - Center for M-Government platform For all mobile applications services. Please Browse Gallery",
                        "desc": "Please Visit Mobile Application Gallery Government in http://gamma.malaysia.gov.my",
                        "text": "<p>&nbsp;Please Visit Mobile Application Gallery Government in:</p>",
                        "active": "True",
                        "insert_date": "2017-03-26 16:40:04.323753+00:00",
                        "last_modified": "2017-03-26 16:45:38.177188+00:00",
                        "idcategory": "Pengumuman",
                        "date_publish": "2017-03-26 16:00:00+00:00",
                        "date_end": "2017-03-28 16:00:00+00:00",
                        "link": "http://gamma.malaysia.gov.my",
                        "year": "2017",
                        "archive": "False",
                        "title": ""
                    },
                    {
                        "id": "4",
                        "name": "Penamatan Perkhidmatan e-Lodgement Suruhanjaya Syarikat Malaysia(SSM) melalui Portal MyGovernment",
                        "desc": "",
                        "text": "<p>Penamatan Perkhidmatan e-Lodgement Suruhanjaya Syarikat Malaysia(SSM) melalui Portal MyGovernment telah ditamatkan bermula 1 Mac 2016. Sila layari www.ssm.gov.my bagi mendapatkan maklumat lanjut mengenai perkhidmatan dalam talian yang ditawarkan.</p>",
                        "active": "False",
                        "insert_date": "2017-02-17 06:47:17.695690+00:00",
                        "last_modified": "2017-03-30 14:16:53.506340+00:00",
                        "idcategory": "Pengumuman",
                        "date_publish": "2017-02-18 14:46:00+00:00",
                        "date_end": "2017-02-19 07:00:00+00:00",
                        "link": "https:/",
                        "year": "2017",
                        "archive": "False",
                        "title": ""
                    },
                    {
                        "id": "8",
                        "name": "Public Sector Data Dictionary (DDSA)",
                        "desc": "defined as evidence of a standard data includes the name of the element",
                        "text": "<p><span>Public Sector Data Dictionary (DDSA) was defined as evidence of a standard data includes data element name, alias (another name element data), a brief description of data, data element size, the type of terrain and the rationale for the data element. It also sets standards for specific elements of data code to be adopted by all public sector agencies.</span></p>",
                        "active": "True",
                        "insert_date": "2017-02-21 08:16:03.154961+00:00",
                        "last_modified": "2017-03-26 17:18:21.670515+00:00",
                        "idcategory": "Pengumuman",
                        "date_publish": "2017-02-20 16:00:00+00:00",
                        "date_end": "2017-08-31 16:00:00+00:00",
                        "link": "http://sddsa.mampu.gov.my",
                        "year": "2017",
                        "archive": "False",
                        "title": ""
                    },
                    {
                        "id": "22",
                        "name": "Kekosongan Jawatan Pembantu Tadbir Kewangan (PT(KEW)) Gred W26 Perkhidmatan Gunasama Persekutuan",
                        "desc": "Kekosongan Jawatan Pembantu Tadbir Kewangan (PT(KEW)) Gred W26 Perkhidmatan Gunasama Persekutuan Di",
                        "text": "<p style=\"text-align: justify;\">Pemakluman Urusan Persediaan Pengisian Satu (1) Kekosongan Jawatan Pembantu Tadbir Kewangan (PT(KEW)) Gred W26 Perkhidmatan Gunasama Persekutuan Di Penjara Simpang Renggam, Johor</p><p style=\"text-align: justify;\"><a href=\"http://docs.jpa.gov.my/docs/se/2017/se16032017.pdf\" target=\"_blank\">SURAT EDARAN JPA.BK(S)134/8/62 Jld. 4(1)&nbsp;</a>/&nbsp;<a href=\"http://docs.jpa.gov.my/docs/se/2017/Lampiran_A_se16032017.pdf\" target=\"_blank\">Lampiran A</a>&nbsp;/&nbsp;<a href=\"http://docs.jpa.gov.my/docs/se/2017/Lampiran_B_se16032017.pdf\" target=\"_blank\">Lampiran B&nbsp;</a>/&nbsp;<a href=\"http://docs.jpa.gov.my/docs/se/2017/Lampiran_C_se16032017.pdf\" target=\"_blank\">Lampiran C</a></p>",
                        "active": "True",
                        "insert_date": "2017-03-27 13:54:53.516297+00:00",
                        "last_modified": "2017-03-27 15:40:04.509843+00:00",
                        "idcategory": "Kerjaya",
                        "date_publish": "2017-03-27 13:50:00+00:00",
                        "date_end": "2017-04-07 16:00:00+00:00",
                        "link": "http://www.jpa.gov.my/index.php?option=com_content&view=article&id=4082:surat-edaran-jpa-bk-s-134-8-62-jld-4-1&catid=507:pengumuman&Itemid=1332&lang=ms",
                        "year": "2017",
                        "archive": "False",
                        "title": ""
                    },
                    {
                        "id": "21",
                        "name": "Perkhidmatan Membekal Dan Menghantar Rangsum Penerbangan Untuk Pangkalan Udara, Jabatan Bomba Dan Penyelamat Malaysia Bagi Tempoh Dua (2) Tahun",
                        "desc": "Perkhidmatan membekal dan menghantar rangsum penerbangan untuk pangkalan udara, jabatan bomba dan pe",
                        "text": "<table width=\"100%\" border=\"0\" cellspacing=\"0\" cellpadding=\"0\"><tbody><tr><td width=\"35%\"><p>&nbsp;</p><p><strong>Tarikh Pengiklanan</strong></p></td><td style=\"text-align: justify;\" colspan=\"3\"><p>&nbsp;</p><p>: 24/03/2017</p></td></tr><tr><td><p><strong>Tarikh Tutup</strong></p></td><td style=\"text-align: justify;\" colspan=\"3\"><p>: 19/04/2017 12:00 PM</p></td></tr><tr><td><p><strong>Jangkamasa Sahlaku Tender (Hari)</strong></p></td><td style=\"text-align: justify;\" colspan=\"3\"><p>: 180</p></td></tr><tr><td><p><strong>Kementerian</strong></p></td><td style=\"text-align: justify;\" colspan=\"3\"><p>: KEMENTERIAN PERUMAHAN DAN KERAJAAN TEMPATAN</p></td></tr><tr><td><p><strong>Jabatan</strong></p></td><td style=\"text-align: justify;\" colspan=\"3\"><p>: JABATAN BOMBA DAN PENYELAMAT MALAYSIA</p></td></tr><tr><td><p><strong>PTJ</strong></p></td><td style=\"text-align: justify;\" colspan=\"3\"><p>: PEJ KEW I.PEJABAT BOMBA &amp; PENYELAMAT MY</p></td></tr><tr><td><p><strong>No. Tender</strong></p></td><td style=\"text-align: justify;\" colspan=\"3\"><p>: (i) JBPM:T/(S)/02/2017</p><p>: (ii) JBPM:T/(S)/16/2017 &nbsp;&nbsp;</p></td></tr><tr><td><p><strong>Tajuk Tender</strong></p></td><td style=\"text-align: justify;\" colspan=\"3\"><p>: PERKHIDMATAN MEMBEKAL DAN MENGHANTAR RANGSUM PENERBANGAN UNTUK PANGKALAN UDARA, JABATAN BOMBA DAN PENYELAMAT MALAYSIA BAGI TEMPOH DUA (2) TAHUN</p></td></tr><tr><td><p><strong>Perihal</strong></p></td><td style=\"text-align: justify;\" colspan=\"3\"><p>: PERKHIDMATAN MEMBEKAL DAN MENGHANTAR RANGSUM PENERBANGAN UNTUK PANGKALAN UDARA, JABATAN BOMBA DAN PENYELAMAT MALAYSIA BAGI TEMPOH DUA (2) TAHUN - (HANYA PENAMA DI SIJIL AKUAN PENDAFTARAN SYARIKAT YANG BERDAFTAR DGN KEMENTERIAN KEWANGAN SAHAJA BOLEH MENGHADIRI SESI TAKLIMAT TENDER)</p></td></tr><tr><td><p><strong>Status Pembekal</strong></p></td><td style=\"text-align: justify;\" colspan=\"3\"><p>: Kesemua</p></td></tr><tr><td><p><strong>Jenis Tender</strong></p></td><td style=\"text-align: justify;\" colspan=\"3\"><p>: Terbuka Untuk Semua &nbsp;&nbsp;</p></td></tr><tr><td><p><strong>Dokumen Tender&nbsp;</strong><strong>Yang Ada/ Boleh Diperolehi</strong></p></td><td style=\"text-align: justify;\" colspan=\"3\"><p>: Penender yang berminat diminta datang/menghubungi Pusat Perhubungan (Telecenter) berkenaan dengan mengemukakan Nombor Pendaftaran K. Kewangan untuk mendapatkan dokumen tender secara atas talian.Alamat Pusat Perhubungan (Telecenter)</p></td></tr><tr><td><p><strong>Pegawai Untuk Dihubungi</strong></p></td><td><p><strong>No. Telefon Pegawai</strong></p></td><td><p><strong>No. Fax Pegawai</strong></p></td><td><p><strong>Email Pegawai</strong></p></td></tr><tr><td><p>ENCIK AHMAD YUSZAIRY BIN MOHAMAD</p></td><td><p>03-8892 7686</p></td><td><p>03-8881 1520</p></td><td><p>yuszairy@bomba.gov.my</p></td></tr><tr><td><p>ENCIK MOHD SAIFULLAH BIN ROSLAN</p></td><td><p>03-8892 7685</p></td><td><p>03-8881 1520</p></td><td><p>saifullah@bomba.gov.my</p></td></tr></tbody></table>",
                        "active": "True",
                        "insert_date": "2017-03-27 10:26:47.767296+00:00",
                        "last_modified": "2017-03-27 15:40:44.140859+00:00",
                        "idcategory": "Tender",
                        "date_publish": "2017-03-27 10:21:00+00:00",
                        "date_end": "2017-04-19 15:00:00+00:00",
                        "link": "http://www.kpkt.gov.my/index.php/pages/view/149",
                        "year": "2017",
                        "archive": "False",
                        "title": ""
                    },
                    {
                        "id": "25",
                        "name": "Jawatan Kosong Dewan Bahasa Dan Pustaka",
                        "desc": "Jawatan Kosong Dewan Bahasa Dan Pustaka",
                        "text": "<p><span>Dewan Bahasa dan Pustaka dengan ini mempelawa warga Malaysia yang berkelayakan dan berumur tidak kurang daripada 18 tahun pada tarikh tutup iklan jawatan untuk memohon jawatan yang berikut:</span></p><ol><li>Akauntan Gred WA41</li><li>Penolong Pegawai Tadbir Gred N29</li><li>Juruteknik Komputer Gred FT19 &nbsp;</li><li>Pembantu Penerbitan Gred N19</li><li>Pembantu Penerbitan Gred N19</li><li>Pembantu Pemuliharaan Gred S19</li><li>Pereka Gred B19</li><li>Pembantu Awam Gred H11</li><li>Pembantu Operasi Gred N11</li><li>Pembantu Pemasaran Kanan&nbsp;</li></ol><p><span><a href=\"http://laman.dbp.gov.my/lamandbp/download.php?FilePoolID=953\">[Maklumat lanjut</a><a href=\"http://laman.dbp.gov.my/lamandbp/download.php?FilePoolID=925\">]</a>&nbsp; [<a href=\"http://laman.dbp.gov.my/lamandbp/download.php?FilePoolID=886\">Borang Jawatan Kosong DBP</a><span>]<br /></span><br /><strong>Tarikh tutup: 3 April 2017</strong></span></p>",
                        "active": "True",
                        "insert_date": "2017-03-27 15:15:13.870899+00:00",
                        "last_modified": "2017-03-27 15:39:12.985477+00:00",
                        "idcategory": "Kerjaya",
                        "date_publish": "2017-03-27 15:13:00+00:00",
                        "date_end": "2017-04-29 16:00:00+00:00",
                        "link": "http://laman.dbp.gov.my/lamandbp",
                        "year": "2017",
                        "archive": "False",
                        "title": ""
                    },
                    {
                        "id": "20",
                        "name": "Membekal Dan Menghantar Baju T-Shirt Petugas Untuk Kegunaan Pilihan Raya Umum Ke-14 Suruhanjaya Pilihan Raya Malaysia",
                        "desc": "Membekal dan menghantar baju t-shirt petugas untuk kegunaan pilihan raya umum ke-14 suruhanjaya pili",
                        "text": "<table width=\"100%\" border=\"0\" cellspacing=\"0\" cellpadding=\"1\"><tbody><tr><td width=\"40%\"><p>&nbsp;</p><p><strong>Tarikh Pengiklanan</strong></p></td><td colspan=\"3\"><p>&nbsp;</p><p>22/03/2017</p></td></tr><tr><td><p><strong>Tarikh Tutup</strong></p></td><td colspan=\"3\"><p>12/04/2017 12:00 PM</p></td></tr><tr><td><p><strong>Jangkamasa Sahlaku Tender (Hari)</strong></p></td><td colspan=\"3\"><p>180</p></td></tr><tr><td><p><strong>Kementerian</strong></p></td><td colspan=\"3\"><p>JABATAN PERDANA MENTERI</p></td></tr><tr><td><p><strong>Jabatan</strong></p></td><td colspan=\"3\"><p>SURUHANJAYA PILIHANRAYA</p></td></tr><tr><td><p><strong>PTJ</strong></p></td><td colspan=\"3\"><p>SURUHANJAYA PILIHANRAYA MALAYSIA</p></td></tr><tr><td><p><strong>No. Tender</strong></p></td><td colspan=\"3\"><p>X0101010100170008</p></td></tr><tr><td><p><strong>Tajuk Tender</strong></p></td><td colspan=\"3\"><p>MEMBEKAL DAN MENGHANTAR BAJU T-SHIRT PETUGAS UNTUK KEGUNAAN PILIHAN RAYA UMUM KE-14 SURUHANJAYA PILIHAN RAYA MALAYSIA</p></td></tr><tr><td><p><strong>Perihal</strong></p></td><td colspan=\"3\"><p>MEMBEKAL DAN MENGHANTAR BAJU T-SHIRT PETUGAS UNTUK KEGUNAAN PILIHAN RAYA UMUM KE-14 SURUHANJAYA PILIHAN RAYA MALAYSIA</p></td></tr><tr><td><p><strong>Status Pembekal</strong></p></td><td colspan=\"3\"><p>Kesemua</p></td></tr><tr><td><p><strong>Jenis Tender</strong></p></td><td colspan=\"3\"><p>Terbuka Untuk Semua</p></td></tr><tr><td style=\"text-align: justify;\"><p style=\"text-align: left;\"><strong>Dokumen Tender Yang Ada/ Boleh Diperolehi</strong></p></td><td style=\"text-align: justify;\" colspan=\"3\"><p>Penender yang berminat diminta datang/menghubungi Pusat Perhubungan (Telecenter) berkenaan dengan mengemukakan Nombor Pendaftaran K. Kewangan untuk mendapatkan dokumen tender secara atas talian.</p></td></tr><tr><td style=\"text-align: left; vertical-align: bottom;\"><p><strong>Pegawai Untuk Dihubungi</strong></p></td><td style=\"text-align: left; vertical-align: bottom;\"><p><strong>No. Telefon Pegawai</strong></p></td><td style=\"text-align: left; vertical-align: bottom;\"><p><strong>No. Fax Pegawai</strong></p></td><td style=\"text-align: left; vertical-align: bottom;\"><p><strong>Email Pegawai</strong></p></td></tr><tr><td style=\"text-align: left; vertical-align: top;\"><p>ENCIK MUHAMAD AZIM BIN MUHAMAD NOR (SPESIFIKASI BEKALAN)</p></td><td style=\"text-align: left; vertical-align: top;\"><p>03-8892 7247</p></td><td style=\"text-align: left; vertical-align: top;\"><p>03-8892 7001</p></td><td style=\"text-align: left; vertical-align: top;\"><p>azim@spr.gov.my</p></td></tr><tr><td style=\"text-align: left; vertical-align: top;\"><p>PUAN NORAZLIN BINTI MANSOR (BAHAGIAN KEWANGAN DAN AM)</p></td><td style=\"text-align: left; vertical-align: top;\"><p>03-8892 7297</p></td><td style=\"text-align: left; vertical-align: top;\"><p>03-8892 7354</p></td><td style=\"text-align: left; vertical-align: top;\"><p>norazlin@spr.gov.my</p></td></tr><tr><td style=\"text-align: left; vertical-align: top;\"><p>PUAN RUHEZA BINTI ZAKARIAH (BAHAGIAN KEWANGAN DAN AM)</p></td><td style=\"text-align: left; vertical-align: top;\"><p>03-8892 7295</p></td><td style=\"text-align: left; vertical-align: top;\"><p>03-8892 7354</p></td><td style=\"text-align: left; vertical-align: top;\"><p>ruheza@spr.gov.my</p></td></tr></tbody></table>",
                        "active": "True",
                        "insert_date": "2017-03-27 09:55:57.075155+00:00",
                        "last_modified": "2017-03-27 15:41:17.984646+00:00",
                        "idcategory": "Tender",
                        "date_publish": "2017-03-27 09:55:00+00:00",
                        "date_end": "2017-04-12 15:00:00+00:00",
                        "link": "http://www.spr.gov.my/media/tendersebutharga/TENDER3.2017.pdf",
                        "year": "2017",
                        "archive": "False",
                        "title": ""
                    },
                    {
                        "id": "26",
                        "name": "testin",
                        "desc": "testing",
                        "text": "<p>testing</p>",
                        "active": "True",
                        "insert_date": "2017-03-28 14:52:08.548331+00:00",
                        "last_modified": "2017-03-28 14:59:24.500990+00:00",
                        "idcategory": "Promosi",
                        "date_publish": "2016-10-01 04:00:00+00:00",
                        "date_end": "2016-12-01 15:00:00+00:00",
                        "link": "https:/",
                        "year": "2017",
                        "archive": "False",
                        "title": ""
                    }
                ]
            },
            {
                "Category": [
                    {
                        "id": "18",
                        "name": "LHDN provides e-filing of income tax refunds for Electronic Transfers",
                        "desc": "LHDN provides e-filing of income tax refunds for Electronic Transfers",
                        "text": "<p><span>MINIMUM REQUIREMENTS </span></p><p>&nbsp;</p><ul><li>Microsoft Windows 7 (latest service pack), Linux or Macintosh.</li><li>Internet Explorer 11.0, Microsoft Edge, 44.0 Mozilla Firefox, Google Chrome 46.0 or Safari 5.</li><li>TAXPAYER'S NEW FIRST TIME OR TO REPORT EARNINGS / above RM 450,000</li></ul><p>&nbsp;</p><p><span>Informed that taxpayers who first reported income equals or exceeds &pound; 450,000 through the delivery form for e-Filing must present / IRB branches close contact to make income verification. This procedure is to avoid the possibility of a mistake entering the amount of income by taxpayers. This procedure does not apply to taxpayers who made via e-Filing Tax Agent.</span></p><p><span lang=\"en\">This procedure does not apply to taxpayers who made via e-Filing Tax Agent.</span></p><p><span lang=\"en\">&nbsp;</span></p>",
                        "active": "True",
                        "insert_date": "2017-03-26 16:52:55.065626+00:00",
                        "last_modified": "2017-03-26 16:52:58.032053+00:00",
                        "idcategory": "Pengumuman",
                        "date_publish": "2017-03-26 16:00:00+00:00",
                        "date_end": "2017-03-29 16:00:00+00:00",
                        "link": "https://ez.hasil.gov.my/CI",
                        "year": "2017",
                        "archive": "False",
                        "title": ""
                    },
                    {
                        "id": "19",
                        "name": "MYEG - Create an account to access all our services including road tax renewal, PDRM summons checking, zakat payment, and more.",
                        "desc": "Create an account to access all our services including road tax renewal, PDRM summons checking",
                        "text": "<p>Please visit&nbsp;<a href=\"https://www.myeg.com.my/\" target=\"_blank\">https://www.myeg.com.my/</a> to&nbsp;&nbsp;Create an account to access all our services including road tax renewal, PDRM summons checking, zakat payment, and more.</p>",
                        "active": "True",
                        "insert_date": "2017-03-26 17:01:41.500298+00:00",
                        "last_modified": "2017-03-26 17:03:04.904738+00:00",
                        "idcategory": "Pengumuman",
                        "date_publish": "2017-03-26 16:00:00+00:00",
                        "date_end": "2017-03-29 16:00:00+00:00",
                        "link": "https://www.myeg.com.my",
                        "year": "2017",
                        "archive": "False",
                        "title": ""
                    },
                    {
                        "id": "17",
                        "name": "GAMMA - Center for M-Government platform For all mobile applications services. Please Browse Gallery",
                        "desc": "Please Visit Mobile Application Gallery Government in http://gamma.malaysia.gov.my",
                        "text": "<p>&nbsp;Please Visit Mobile Application Gallery Government in:</p>",
                        "active": "True",
                        "insert_date": "2017-03-26 16:40:04.323753+00:00",
                        "last_modified": "2017-03-26 16:45:38.177188+00:00",
                        "idcategory": "Pengumuman",
                        "date_publish": "2017-03-26 16:00:00+00:00",
                        "date_end": "2017-03-28 16:00:00+00:00",
                        "link": "http://gamma.malaysia.gov.my",
                        "year": "2017",
                        "archive": "False",
                        "title": ""
                    },
                    {
                        "id": "4",
                        "name": "Penamatan Perkhidmatan e-Lodgement Suruhanjaya Syarikat Malaysia(SSM) melalui Portal MyGovernment",
                        "desc": "",
                        "text": "<p>Penamatan Perkhidmatan e-Lodgement Suruhanjaya Syarikat Malaysia(SSM) melalui Portal MyGovernment telah ditamatkan bermula 1 Mac 2016. Sila layari www.ssm.gov.my bagi mendapatkan maklumat lanjut mengenai perkhidmatan dalam talian yang ditawarkan.</p>",
                        "active": "False",
                        "insert_date": "2017-02-17 06:47:17.695690+00:00",
                        "last_modified": "2017-03-30 14:16:53.506340+00:00",
                        "idcategory": "Pengumuman",
                        "date_publish": "2017-02-18 14:46:00+00:00",
                        "date_end": "2017-02-19 07:00:00+00:00",
                        "link": "https:/",
                        "year": "2017",
                        "archive": "False",
                        "title": ""
                    },
                    {
                        "id": "8",
                        "name": "Public Sector Data Dictionary (DDSA)",
                        "desc": "defined as evidence of a standard data includes the name of the element",
                        "text": "<p><span>Public Sector Data Dictionary (DDSA) was defined as evidence of a standard data includes data element name, alias (another name element data), a brief description of data, data element size, the type of terrain and the rationale for the data element. It also sets standards for specific elements of data code to be adopted by all public sector agencies.</span></p>",
                        "active": "True",
                        "insert_date": "2017-02-21 08:16:03.154961+00:00",
                        "last_modified": "2017-03-26 17:18:21.670515+00:00",
                        "idcategory": "Pengumuman",
                        "date_publish": "2017-02-20 16:00:00+00:00",
                        "date_end": "2017-08-31 16:00:00+00:00",
                        "link": "http://sddsa.mampu.gov.my",
                        "year": "2017",
                        "archive": "False",
                        "title": ""
                    },
                    {
                        "id": "22",
                        "name": "Kekosongan Jawatan Pembantu Tadbir Kewangan (PT(KEW)) Gred W26 Perkhidmatan Gunasama Persekutuan",
                        "desc": "Kekosongan Jawatan Pembantu Tadbir Kewangan (PT(KEW)) Gred W26 Perkhidmatan Gunasama Persekutuan Di",
                        "text": "<p style=\"text-align: justify;\">Pemakluman Urusan Persediaan Pengisian Satu (1) Kekosongan Jawatan Pembantu Tadbir Kewangan (PT(KEW)) Gred W26 Perkhidmatan Gunasama Persekutuan Di Penjara Simpang Renggam, Johor</p><p style=\"text-align: justify;\"><a href=\"http://docs.jpa.gov.my/docs/se/2017/se16032017.pdf\" target=\"_blank\">SURAT EDARAN JPA.BK(S)134/8/62 Jld. 4(1)&nbsp;</a>/&nbsp;<a href=\"http://docs.jpa.gov.my/docs/se/2017/Lampiran_A_se16032017.pdf\" target=\"_blank\">Lampiran A</a>&nbsp;/&nbsp;<a href=\"http://docs.jpa.gov.my/docs/se/2017/Lampiran_B_se16032017.pdf\" target=\"_blank\">Lampiran B&nbsp;</a>/&nbsp;<a href=\"http://docs.jpa.gov.my/docs/se/2017/Lampiran_C_se16032017.pdf\" target=\"_blank\">Lampiran C</a></p>",
                        "active": "True",
                        "insert_date": "2017-03-27 13:54:53.516297+00:00",
                        "last_modified": "2017-03-27 15:40:04.509843+00:00",
                        "idcategory": "Kerjaya",
                        "date_publish": "2017-03-27 13:50:00+00:00",
                        "date_end": "2017-04-07 16:00:00+00:00",
                        "link": "http://www.jpa.gov.my/index.php?option=com_content&view=article&id=4082:surat-edaran-jpa-bk-s-134-8-62-jld-4-1&catid=507:pengumuman&Itemid=1332&lang=ms",
                        "year": "2017",
                        "archive": "False",
                        "title": ""
                    },
                    {
                        "id": "21",
                        "name": "Perkhidmatan Membekal Dan Menghantar Rangsum Penerbangan Untuk Pangkalan Udara, Jabatan Bomba Dan Penyelamat Malaysia Bagi Tempoh Dua (2) Tahun",
                        "desc": "Perkhidmatan membekal dan menghantar rangsum penerbangan untuk pangkalan udara, jabatan bomba dan pe",
                        "text": "<table width=\"100%\" border=\"0\" cellspacing=\"0\" cellpadding=\"0\"><tbody><tr><td width=\"35%\"><p>&nbsp;</p><p><strong>Tarikh Pengiklanan</strong></p></td><td style=\"text-align: justify;\" colspan=\"3\"><p>&nbsp;</p><p>: 24/03/2017</p></td></tr><tr><td><p><strong>Tarikh Tutup</strong></p></td><td style=\"text-align: justify;\" colspan=\"3\"><p>: 19/04/2017 12:00 PM</p></td></tr><tr><td><p><strong>Jangkamasa Sahlaku Tender (Hari)</strong></p></td><td style=\"text-align: justify;\" colspan=\"3\"><p>: 180</p></td></tr><tr><td><p><strong>Kementerian</strong></p></td><td style=\"text-align: justify;\" colspan=\"3\"><p>: KEMENTERIAN PERUMAHAN DAN KERAJAAN TEMPATAN</p></td></tr><tr><td><p><strong>Jabatan</strong></p></td><td style=\"text-align: justify;\" colspan=\"3\"><p>: JABATAN BOMBA DAN PENYELAMAT MALAYSIA</p></td></tr><tr><td><p><strong>PTJ</strong></p></td><td style=\"text-align: justify;\" colspan=\"3\"><p>: PEJ KEW I.PEJABAT BOMBA &amp; PENYELAMAT MY</p></td></tr><tr><td><p><strong>No. Tender</strong></p></td><td style=\"text-align: justify;\" colspan=\"3\"><p>: (i) JBPM:T/(S)/02/2017</p><p>: (ii) JBPM:T/(S)/16/2017 &nbsp;&nbsp;</p></td></tr><tr><td><p><strong>Tajuk Tender</strong></p></td><td style=\"text-align: justify;\" colspan=\"3\"><p>: PERKHIDMATAN MEMBEKAL DAN MENGHANTAR RANGSUM PENERBANGAN UNTUK PANGKALAN UDARA, JABATAN BOMBA DAN PENYELAMAT MALAYSIA BAGI TEMPOH DUA (2) TAHUN</p></td></tr><tr><td><p><strong>Perihal</strong></p></td><td style=\"text-align: justify;\" colspan=\"3\"><p>: PERKHIDMATAN MEMBEKAL DAN MENGHANTAR RANGSUM PENERBANGAN UNTUK PANGKALAN UDARA, JABATAN BOMBA DAN PENYELAMAT MALAYSIA BAGI TEMPOH DUA (2) TAHUN - (HANYA PENAMA DI SIJIL AKUAN PENDAFTARAN SYARIKAT YANG BERDAFTAR DGN KEMENTERIAN KEWANGAN SAHAJA BOLEH MENGHADIRI SESI TAKLIMAT TENDER)</p></td></tr><tr><td><p><strong>Status Pembekal</strong></p></td><td style=\"text-align: justify;\" colspan=\"3\"><p>: Kesemua</p></td></tr><tr><td><p><strong>Jenis Tender</strong></p></td><td style=\"text-align: justify;\" colspan=\"3\"><p>: Terbuka Untuk Semua &nbsp;&nbsp;</p></td></tr><tr><td><p><strong>Dokumen Tender&nbsp;</strong><strong>Yang Ada/ Boleh Diperolehi</strong></p></td><td style=\"text-align: justify;\" colspan=\"3\"><p>: Penender yang berminat diminta datang/menghubungi Pusat Perhubungan (Telecenter) berkenaan dengan mengemukakan Nombor Pendaftaran K. Kewangan untuk mendapatkan dokumen tender secara atas talian.Alamat Pusat Perhubungan (Telecenter)</p></td></tr><tr><td><p><strong>Pegawai Untuk Dihubungi</strong></p></td><td><p><strong>No. Telefon Pegawai</strong></p></td><td><p><strong>No. Fax Pegawai</strong></p></td><td><p><strong>Email Pegawai</strong></p></td></tr><tr><td><p>ENCIK AHMAD YUSZAIRY BIN MOHAMAD</p></td><td><p>03-8892 7686</p></td><td><p>03-8881 1520</p></td><td><p>yuszairy@bomba.gov.my</p></td></tr><tr><td><p>ENCIK MOHD SAIFULLAH BIN ROSLAN</p></td><td><p>03-8892 7685</p></td><td><p>03-8881 1520</p></td><td><p>saifullah@bomba.gov.my</p></td></tr></tbody></table>",
                        "active": "True",
                        "insert_date": "2017-03-27 10:26:47.767296+00:00",
                        "last_modified": "2017-03-27 15:40:44.140859+00:00",
                        "idcategory": "Tender",
                        "date_publish": "2017-03-27 10:21:00+00:00",
                        "date_end": "2017-04-19 15:00:00+00:00",
                        "link": "http://www.kpkt.gov.my/index.php/pages/view/149",
                        "year": "2017",
                        "archive": "False",
                        "title": ""
                    },
                    {
                        "id": "25",
                        "name": "Jawatan Kosong Dewan Bahasa Dan Pustaka",
                        "desc": "Jawatan Kosong Dewan Bahasa Dan Pustaka",
                        "text": "<p><span>Dewan Bahasa dan Pustaka dengan ini mempelawa warga Malaysia yang berkelayakan dan berumur tidak kurang daripada 18 tahun pada tarikh tutup iklan jawatan untuk memohon jawatan yang berikut:</span></p><ol><li>Akauntan Gred WA41</li><li>Penolong Pegawai Tadbir Gred N29</li><li>Juruteknik Komputer Gred FT19 &nbsp;</li><li>Pembantu Penerbitan Gred N19</li><li>Pembantu Penerbitan Gred N19</li><li>Pembantu Pemuliharaan Gred S19</li><li>Pereka Gred B19</li><li>Pembantu Awam Gred H11</li><li>Pembantu Operasi Gred N11</li><li>Pembantu Pemasaran Kanan&nbsp;</li></ol><p><span><a href=\"http://laman.dbp.gov.my/lamandbp/download.php?FilePoolID=953\">[Maklumat lanjut</a><a href=\"http://laman.dbp.gov.my/lamandbp/download.php?FilePoolID=925\">]</a>&nbsp; [<a href=\"http://laman.dbp.gov.my/lamandbp/download.php?FilePoolID=886\">Borang Jawatan Kosong DBP</a><span>]<br /></span><br /><strong>Tarikh tutup: 3 April 2017</strong></span></p>",
                        "active": "True",
                        "insert_date": "2017-03-27 15:15:13.870899+00:00",
                        "last_modified": "2017-03-27 15:39:12.985477+00:00",
                        "idcategory": "Kerjaya",
                        "date_publish": "2017-03-27 15:13:00+00:00",
                        "date_end": "2017-04-29 16:00:00+00:00",
                        "link": "http://laman.dbp.gov.my/lamandbp",
                        "year": "2017",
                        "archive": "False",
                        "title": ""
                    },
                    {
                        "id": "20",
                        "name": "Membekal Dan Menghantar Baju T-Shirt Petugas Untuk Kegunaan Pilihan Raya Umum Ke-14 Suruhanjaya Pilihan Raya Malaysia",
                        "desc": "Membekal dan menghantar baju t-shirt petugas untuk kegunaan pilihan raya umum ke-14 suruhanjaya pili",
                        "text": "<table width=\"100%\" border=\"0\" cellspacing=\"0\" cellpadding=\"1\"><tbody><tr><td width=\"40%\"><p>&nbsp;</p><p><strong>Tarikh Pengiklanan</strong></p></td><td colspan=\"3\"><p>&nbsp;</p><p>22/03/2017</p></td></tr><tr><td><p><strong>Tarikh Tutup</strong></p></td><td colspan=\"3\"><p>12/04/2017 12:00 PM</p></td></tr><tr><td><p><strong>Jangkamasa Sahlaku Tender (Hari)</strong></p></td><td colspan=\"3\"><p>180</p></td></tr><tr><td><p><strong>Kementerian</strong></p></td><td colspan=\"3\"><p>JABATAN PERDANA MENTERI</p></td></tr><tr><td><p><strong>Jabatan</strong></p></td><td colspan=\"3\"><p>SURUHANJAYA PILIHANRAYA</p></td></tr><tr><td><p><strong>PTJ</strong></p></td><td colspan=\"3\"><p>SURUHANJAYA PILIHANRAYA MALAYSIA</p></td></tr><tr><td><p><strong>No. Tender</strong></p></td><td colspan=\"3\"><p>X0101010100170008</p></td></tr><tr><td><p><strong>Tajuk Tender</strong></p></td><td colspan=\"3\"><p>MEMBEKAL DAN MENGHANTAR BAJU T-SHIRT PETUGAS UNTUK KEGUNAAN PILIHAN RAYA UMUM KE-14 SURUHANJAYA PILIHAN RAYA MALAYSIA</p></td></tr><tr><td><p><strong>Perihal</strong></p></td><td colspan=\"3\"><p>MEMBEKAL DAN MENGHANTAR BAJU T-SHIRT PETUGAS UNTUK KEGUNAAN PILIHAN RAYA UMUM KE-14 SURUHANJAYA PILIHAN RAYA MALAYSIA</p></td></tr><tr><td><p><strong>Status Pembekal</strong></p></td><td colspan=\"3\"><p>Kesemua</p></td></tr><tr><td><p><strong>Jenis Tender</strong></p></td><td colspan=\"3\"><p>Terbuka Untuk Semua</p></td></tr><tr><td style=\"text-align: justify;\"><p style=\"text-align: left;\"><strong>Dokumen Tender Yang Ada/ Boleh Diperolehi</strong></p></td><td style=\"text-align: justify;\" colspan=\"3\"><p>Penender yang berminat diminta datang/menghubungi Pusat Perhubungan (Telecenter) berkenaan dengan mengemukakan Nombor Pendaftaran K. Kewangan untuk mendapatkan dokumen tender secara atas talian.</p></td></tr><tr><td style=\"text-align: left; vertical-align: bottom;\"><p><strong>Pegawai Untuk Dihubungi</strong></p></td><td style=\"text-align: left; vertical-align: bottom;\"><p><strong>No. Telefon Pegawai</strong></p></td><td style=\"text-align: left; vertical-align: bottom;\"><p><strong>No. Fax Pegawai</strong></p></td><td style=\"text-align: left; vertical-align: bottom;\"><p><strong>Email Pegawai</strong></p></td></tr><tr><td style=\"text-align: left; vertical-align: top;\"><p>ENCIK MUHAMAD AZIM BIN MUHAMAD NOR (SPESIFIKASI BEKALAN)</p></td><td style=\"text-align: left; vertical-align: top;\"><p>03-8892 7247</p></td><td style=\"text-align: left; vertical-align: top;\"><p>03-8892 7001</p></td><td style=\"text-align: left; vertical-align: top;\"><p>azim@spr.gov.my</p></td></tr><tr><td style=\"text-align: left; vertical-align: top;\"><p>PUAN NORAZLIN BINTI MANSOR (BAHAGIAN KEWANGAN DAN AM)</p></td><td style=\"text-align: left; vertical-align: top;\"><p>03-8892 7297</p></td><td style=\"text-align: left; vertical-align: top;\"><p>03-8892 7354</p></td><td style=\"text-align: left; vertical-align: top;\"><p>norazlin@spr.gov.my</p></td></tr><tr><td style=\"text-align: left; vertical-align: top;\"><p>PUAN RUHEZA BINTI ZAKARIAH (BAHAGIAN KEWANGAN DAN AM)</p></td><td style=\"text-align: left; vertical-align: top;\"><p>03-8892 7295</p></td><td style=\"text-align: left; vertical-align: top;\"><p>03-8892 7354</p></td><td style=\"text-align: left; vertical-align: top;\"><p>ruheza@spr.gov.my</p></td></tr></tbody></table>",
                        "active": "True",
                        "insert_date": "2017-03-27 09:55:57.075155+00:00",
                        "last_modified": "2017-03-27 15:41:17.984646+00:00",
                        "idcategory": "Tender",
                        "date_publish": "2017-03-27 09:55:00+00:00",
                        "date_end": "2017-04-12 15:00:00+00:00",
                        "link": "http://www.spr.gov.my/media/tendersebutharga/TENDER3.2017.pdf",
                        "year": "2017",
                        "archive": "False",
                        "title": ""
                    },
                    {
                        "id": "26",
                        "name": "testin",
                        "desc": "testing",
                        "text": "<p>testing</p>",
                        "active": "True",
                        "insert_date": "2017-03-28 14:52:08.548331+00:00",
                        "last_modified": "2017-03-28 14:59:24.500990+00:00",
                        "idcategory": "Promosi",
                        "date_publish": "2016-10-01 04:00:00+00:00",
                        "date_end": "2016-12-01 15:00:00+00:00",
                        "link": "https:/",
                        "year": "2017",
                        "archive": "False",
                        "title": ""
                    },
                    {
                        "id": "6",
                        "name": "News",
                        "desc": "Displays latest news of government agencies.",
                        "icon": "bertia.png",
                        "sort": "1000",
                        "archive": "False",
                        "insert_date": "2017-05-09 11:04:10.772979+00:00",
                        "last_modified": "2017-07-28 08:43:02.298107+00:00"
                    },
                    {
                        "id": "8",
                        "name": "Promotion",
                        "desc": "Displays latest promotion of government agencies.",
                        "icon": "",
                        "sort": "1000",
                        "archive": "False",
                        "insert_date": "2017-05-09 11:04:10.772979+00:00",
                        "last_modified": "2017-07-28 08:43:02.322971+00:00"
                    },
                    {
                        "id": "9",
                        "name": "Jobs",
                        "desc": "Displays current job vacancies of government agencies.",
                        "icon": "job.png",
                        "sort": "1000",
                        "archive": "False",
                        "insert_date": "2017-05-09 11:04:10.772979+00:00",
                        "last_modified": "2017-07-28 08:43:02.398171+00:00"
                    },
                    {
                        "id": "2",
                        "name": "Announcement",
                        "desc": "Displays latest important announcements of government agencies.",
                        "icon": "a1.png",
                        "sort": "1000",
                        "archive": "False",
                        "insert_date": "2017-05-09 11:04:10.772979+00:00",
                        "last_modified": "2017-08-07 20:53:08.988692+00:00"
                    },
                    {
                        "id": "14",
                        "name": "Tender",
                        "desc": "List of All Government Tender",
                        "icon": "",
                        "sort": "1",
                        "archive": "True",
                        "insert_date": "2017-05-09 11:04:10.772979+00:00",
                        "last_modified": "2017-08-07 20:53:08.994964+00:00"
                    }
                ]
            }
        ]
    }
]